logpulse/__init__.py
logpulse/main.py
logpulse/viz.py
logpulse-0.1.2.dist-info/WHEEL
logpulse-0.1.2.dist-info/METADATA
logpulse-0.1.2.dist-info/RECORD
