Metadata-Version: 2.3
Name: logpulse
Version: 0.1.2
Summary: High-resolution performance logging for Python.
Author: Eren Irmak
Author-email: Eren Irmak <your.email@example.com>
Requires-Dist: pandas>=2.0.0
Requires-Dist: matplotlib>=3.8.0 ; extra == 'viz'
Requires-Dist: seaborn>=0.13.0 ; extra == 'viz'
Requires-Python: >=3.10
Provides-Extra: viz
